{
    "name": "AdminEmploy",
    "fields": [
        {
            "fieldName": "nameAdminEmp",
            "fieldType": "String"
        },
        {
            "fieldName": "password",
            "fieldType": "String"
        }
    ],
    "relationships": [
        {
            "relationshipType": "many-to-one",
            "otherEntityName": "login",
            "otherEntityRelationshipName": "id",
            "relationshipName": "login",
            "otherEntityField": "id"
        },
        {
            "relationshipType": "many-to-one",
            "otherEntityName": "permission",
            "otherEntityRelationshipName": "id",
            "relationshipName": "permission",
            "otherEntityField": "id"
        }
    ],
    "changelogDate": "20200320152600",
    "entityTableName": "admin_employ",
    "dto": "no",
    "pagination": "no",
    "service": "no",
    "jpaMetamodelFiltering": false,
    "fluentMethods": true,
    "readOnly": false,
    "clientRootFolder": "",
    "applications": "*"
}